__init__.py
getrak_middleware_api_python_sdk-1.0.1.dist-info/licenses/LICENSE
getrakmiddlewareapi/__init__.py
getrakmiddlewareapi/api.py
getrakmiddlewareapi/apis/__init__.py
getrakmiddlewareapi/apis/tracker_history.py
getrakmiddlewareapi/apis/vehicles.py
getrakmiddlewareapi/database/__init__.py
getrakmiddlewareapi/database/models/__init__.py
getrakmiddlewareapi/database/models/dataexplained.py
getrakmiddlewareapi/database/models/record.py
getrakmiddlewareapi/database/models/vehicle.py
getrak_middleware_api_python_sdk-1.0.1.dist-info/METADATA
getrak_middleware_api_python_sdk-1.0.1.dist-info/WHEEL
getrak_middleware_api_python_sdk-1.0.1.dist-info/top_level.txt
getrak_middleware_api_python_sdk-1.0.1.dist-info/RECORD
